kg_prometheus/__init__.py
kg_prometheus/builder.py
kg_prometheus/configfile.py
kg_prometheus/configfileext.py
kg_prometheus/option.py
kg_prometheus/py.typed
kg_prometheus/tests/__init__.py
kg_prometheus/tests/test_builder.py
tests/__init__.py
tests/test_builder.py
kg_prometheus-0.8.1.dist-info/LICENSE
kg_prometheus-0.8.1.dist-info/METADATA
kg_prometheus-0.8.1.dist-info/WHEEL
kg_prometheus-0.8.1.dist-info/top_level.txt
kg_prometheus-0.8.1.dist-info/RECORD
