Metadata-Version: 2.1
Name: kg-prometheus
Version: 0.8.1
Summary: KubraGen Builder: Prometheus
Home-page: https://github.com/RangelReale/kg_prometheus
Author: Rangel Reale
Author-email: rangelreale@gmail.com
License: UNKNOWN
Platform: UNKNOWN
Classifier: Programming Language :: Python :: 3
Classifier: License :: OSI Approved :: MIT License
Classifier: Operating System :: OS Independent
Requires-Python: >=3.6
Requires-Dist: kubragen (>=0.8.2)
